03_combinational_circuits/mux/8to1mux/8to1mux.v
module mux8to1 (
    input  wire [7:0] data_in,
    input  wire [2:0] sel,      // 3-bit select for 8-to-1 mux
    output wire       dout
);
    assign dout = data_in[sel];
endmodule


`timescale 1ps/1ps

module mux8to1_tb;

    // Testbench signals
    reg  [7:0] data_in;
    reg  [2:0] sel;
    wire       dout;

    integer i;   // loop variable

    // Instantiate the DUT
    mux8to1 uut (
        .data_in(data_in),
        .sel    (sel),
        .dout   (dout)
    );

    // Dumpfile and dumpvars for VCD
    initial begin
        $dumpfile("mux8to1.vcd");   // VCD file name
        $dumpvars(0, mux8to1_tb);   // Dump all signals in this module and below
    end

    // Stimulus with loop
    initial begin
        // Monitor signals
        $monitor("Time = %0t | data_in = %b | sel = %b | dout = %b",
                 $time, data_in, sel, dout);

        // First data pattern
        data_in = 8'b1010_1101;

        // Loop through all 8 select values
        for (i = 0; i < 8; i = i + 1) begin
            sel = i;
            #10;
        end

        // Second data pattern
        data_in = 8'b0101_0011;

        // Loop again
        for (i = 0; i < 8; i = i + 1) begin
            sel = i;
            #10;
        end

        $display("Simulation finished");
        $finish;
    end

endmodule

03_combinational_circuits/mux/8to1mux/mux8to1.vcd
$date
	Tue Sep 15 19:48:06 2026
$end
$version
	Icarus Verilog
$end
$timescale
	1ps
$end
$scope module mux8to1_tb $end
$var wire 1 ! dout $end
$var reg 8 " data_in [7:0] $end
$var reg 3 # sel [2:0] $end
$var integer 32 $ i [31:0] $end
$scope module uut $end
$var wire 8 % data_in [7:0] $end
$var wire 3 & sel [2:0] $end
$var wire 1 ! dout $end
$upscope $end
$upscope $end
$enddefinitions $end
$comment Show the parameter values. $end
$dumpall
$end
#0
$dumpvars
b0 &
b10101101 %
b0 $
b0 #
b10101101 "
1!
$end
#10
0!
b1 #
b1 &
b1 $
#20
1!
b10 #
b10 &
b10 $
#30
b11 #
b11 &
b11 $
#40
0!
b100 #
b100 &
b100 $
#50
1!
b101 #
b101 &
b101 $
#60
0!
b110 #
b110 &
b110 $
#70
1!
b111 #
b111 &
b111 $
#80
b0 #
b0 &
1!
b1010011 "
b1010011 %
b0 $
#90
b1 #
b1 &
b1 $
#100
0!
b10 #
b10 &
b10 $
#110
b11 #
b11 &
b11 $
#120
1!
b100 #
b100 &
b100 $
#130
0!
b101 #
b101 &
b101 $
#140
1!
b110 #
b110 &
b110 $
#150
0!
b111 #
b111 &
b111 $
#160
b1000 $
