03_combinational_circuits/mux/4to1mux/4to1mux.v
module mux_4to1 (
    input wire a,//I0
    input wire b,//I1
    input wire c,//I2
    input wire d,//I3
    input wire S0,//S0 select line 
    input wire S1,// S1 select line 
    output wire y
);

assign y = (~S1 & ~S0 & a) |
           (~S1 &  S0 & b) |
           ( S1 & ~S0 & c) |
           ( S1 &  S0 & d);
    
endmodule

`timescale 1ps/1ps

module mux_4to1_tb;

    // Inputs
    reg a;
    reg b;
    reg c;
    reg d;
    reg S0;
    reg S1;

    // Output
    wire y;

    // Instantiate the DUT  ← fixed name
    mux_4to1 dut (
        .a   (a),
        .b   (b),
        .c   (c),
        .d   (d),
        .S0 (S0),
        .S1 (S1),
        .y   (y)
    );

    integer i;

    initial begin
        
        $dumpfile("4to1mux.vcd");
        $dumpvars(0, mux_4to1_tb);
        $display("Time\t S1 S0 a b c d | y");
        $display("-------------------");
        $monitor("%0t\t  %b  %b %b %b %b %b | %b", $time, S1 ,S0 , a, b, c, d, y);

        // Exhaustive test using a loop (all 8 combinations)
        for (i = 0; i < 64; i = i + 1) begin
            {S1,S0,a,b,c,d} = i;
            #10;
        end

        $display("-------------------");
        $display("Test completed.");
        $finish;
    end

endmodule




/* 

Output
panda@Panda:~/Verilog/03_combinational_circuits/mux/4to1mux$ vvp 4to1mux.out
VCD info: dumpfile 4to1mux.vcd opened for output.
Time     S1 S0 a b c d | y
-------------------
0         0  0 0 0 0 0 | 0
10        0  0 0 0 0 1 | 0
20        0  0 0 0 1 0 | 0
30        0  0 0 0 1 1 | 0
40        0  0 0 1 0 0 | 0
50        0  0 0 1 0 1 | 0
60        0  0 0 1 1 0 | 0
70        0  0 0 1 1 1 | 0
80        0  0 1 0 0 0 | 1
90        0  0 1 0 0 1 | 1
100       0  0 1 0 1 0 | 1
110       0  0 1 0 1 1 | 1
120       0  0 1 1 0 0 | 1
130       0  0 1 1 0 1 | 1
140       0  0 1 1 1 0 | 1
150       0  0 1 1 1 1 | 1
160       0  1 0 0 0 0 | 0
170       0  1 0 0 0 1 | 0
180       0  1 0 0 1 0 | 0
190       0  1 0 0 1 1 | 0
200       0  1 0 1 0 0 | 1
210       0  1 0 1 0 1 | 1
220       0  1 0 1 1 0 | 1
230       0  1 0 1 1 1 | 1
240       0  1 1 0 0 0 | 0
250       0  1 1 0 0 1 | 0
260       0  1 1 0 1 0 | 0
270       0  1 1 0 1 1 | 0
280       0  1 1 1 0 0 | 1
290       0  1 1 1 0 1 | 1
300       0  1 1 1 1 0 | 1
310       0  1 1 1 1 1 | 1
320       1  0 0 0 0 0 | 0
330       1  0 0 0 0 1 | 0
340       1  0 0 0 1 0 | 1
350       1  0 0 0 1 1 | 1
360       1  0 0 1 0 0 | 0
370       1  0 0 1 0 1 | 0
380       1  0 0 1 1 0 | 1
390       1  0 0 1 1 1 | 1
400       1  0 1 0 0 0 | 0
410       1  0 1 0 0 1 | 0
420       1  0 1 0 1 0 | 1
430       1  0 1 0 1 1 | 1
440       1  0 1 1 0 0 | 0
450       1  0 1 1 0 1 | 0
460       1  0 1 1 1 0 | 1
470       1  0 1 1 1 1 | 1
480       1  1 0 0 0 0 | 0
490       1  1 0 0 0 1 | 1
500       1  1 0 0 1 0 | 0
510       1  1 0 0 1 1 | 1
520       1  1 0 1 0 0 | 0
530       1  1 0 1 0 1 | 1
540       1  1 0 1 1 0 | 0
550       1  1 0 1 1 1 | 1
560       1  1 1 0 0 0 | 0
570       1  1 1 0 0 1 | 1
580       1  1 1 0 1 0 | 0
590       1  1 1 0 1 1 | 1
600       1  1 1 1 0 0 | 0
610       1  1 1 1 0 1 | 1
620       1  1 1 1 1 0 | 0
630       1  1 1 1 1 1 | 1
-------------------
Test completed.
4to1mux.v:62: $finish called at 640 (1ps)

*/

03_combinational_circuits/mux/4to1mux/4to1mux.vcd
$date
	Tue Sep 15 17:33:48 2026
$end
$version
	Icarus Verilog
$end
$timescale
	1ps
$end
$scope module mux_4to1_tb $end
$var wire 1 ! y $end
$var reg 1 " S0 $end
$var reg 1 # S1 $end
$var reg 1 $ a $end
$var reg 1 % b $end
$var reg 1 & c $end
$var reg 1 ' d $end
$var integer 32 ( i [31:0] $end
$scope module dut $end
$var wire 1 " S0 $end
$var wire 1 # S1 $end
$var wire 1 $ a $end
$var wire 1 % b $end
$var wire 1 & c $end
$var wire 1 ' d $end
$var wire 1 ! y $end
$upscope $end
$upscope $end
$enddefinitions $end
$comment Show the parameter values. $end
$dumpall
$end
#0
$dumpvars
b0 (
0'
0&
0%
0$
0#
0"
0!
$end
#10
1'
b1 (
#20
1&
0'
b10 (
#30
1'
b11 (
#40
1%
0&
0'
b100 (
#50
1'
b101 (
#60
1&
0'
b110 (
#70
1'
b111 (
#80
1!
1$
0%
0&
0'
b1000 (
#90
1'
b1001 (
#100
1&
0'
b1010 (
#110
1'
b1011 (
#120
1%
0&
0'
b1100 (
#130
1'
b1101 (
#140
1&
0'
b1110 (
#150
1'
b1111 (
#160
0!
1"
0$
0%
0&
0'
b10000 (
#170
1'
b10001 (
#180
1&
0'
b10010 (
#190
1'
b10011 (
#200
1!
1%
0&
0'
b10100 (
#210
1'
b10101 (
#220
1&
0'
b10110 (
#230
1'
b10111 (
#240
0!
1$
0%
0&
0'
b11000 (
#250
1'
b11001 (
#260
1&
0'
b11010 (
#270
1'
b11011 (
#280
1!
1%
0&
0'
b11100 (
#290
1'
b11101 (
#300
1&
0'
b11110 (
#310
1'
b11111 (
#320
0!
1#
0"
0$
0%
0&
0'
b100000 (
#330
1'
b100001 (
#340
1!
1&
0'
b100010 (
#350
1'
b100011 (
#360
0!
1%
0&
0'
b100100 (
#370
1'
b100101 (
#380
1!
1&
0'
b100110 (
#390
1'
b100111 (
#400
0!
1$
0%
0&
0'
b101000 (
#410
1'
b101001 (
#420
1!
1&
0'
b101010 (
#430
1'
b101011 (
#440
0!
1%
0&
0'
b101100 (
#450
1'
b101101 (
#460
1!
1&
0'
b101110 (
#470
1'
b101111 (
#480
0!
1"
0$
0%
0&
0'
b110000 (
#490
1!
1'
b110001 (
#500
0!
1&
0'
b110010 (
#510
1!
1'
b110011 (
#520
0!
1%
0&
0'
b110100 (
#530
1!
1'
b110101 (
#540
0!
1&
0'
b110110 (
#550
1!
1'
b110111 (
#560
0!
1$
0%
0&
0'
b111000 (
#570
1!
1'
b111001 (
#580
0!
1&
0'
b111010 (
#590
1!
1'
b111011 (
#600
0!
1%
0&
0'
b111100 (
#610
1!
1'
b111101 (
#620
0!
1&
0'
b111110 (
#630
1!
1'
b111111 (
#640
b1000000 (
