03_combinational_circuits/mux/2to1mux/2to1mux.v
module mux_2to1 (
    input  wire a,
    input  wire b,
    input  wire sel,
    output wire y
);

    assign y = (a & ~sel) | (b & sel);
    
endmodule


`timescale 1ns/1ps

module mux2to1_tb;

    // Inputs
    reg a;
    reg b;
    reg sel;

    // Output
    wire y;

    // Instantiate the DUT  ← fixed name
    mux_2to1 dut (
        .a   (a),
        .b   (b),
        .sel (sel),
        .y   (y)
    );

    integer i;

    initial begin
        
        $dumpfile("2to1mux.vcd");
        $dumpvars(0, mux2to1_tb);
        $display("Time\t sel a b | y");
        $display("-------------------");
        $monitor("%0t\t  %b  %b %b | %b", $time, sel, a, b, y);

        // Exhaustive test using a loop (all 8 combinations)
        for (i = 0; i < 8; i = i + 1) begin
            {sel, a, b} = i;
            #10;
        end

        $display("-------------------");
        $display("Test completed.");
        $finish;
    end

endmodule

03_combinational_circuits/mux/2to1mux/2to1mux.vcd
$date
	Tue Sep 15 09:03:50 2026
$end
$version
	Icarus Verilog
$end
$timescale
	1ps
$end
$scope module mux2to1_tb $end
$var wire 1 ! y $end
$var reg 1 " a $end
$var reg 1 # b $end
$var reg 1 $ sel $end
$var integer 32 % i [31:0] $end
$scope module dut $end
$var wire 1 " a $end
$var wire 1 # b $end
$var wire 1 $ sel $end
$var wire 1 ! y $end
$upscope $end
$upscope $end
$enddefinitions $end
$comment Show the parameter values. $end
$dumpall
$end
#0
$dumpvars
b0 %
0$
0#
0"
0!
$end
#10000
1#
b1 %
#20000
1!
1"
0#
b10 %
#30000
1#
b11 %
#40000
0!
1$
0"
0#
b100 %
#50000
1!
1#
b101 %
#60000
0!
1"
0#
b110 %
#70000
1!
1#
b111 %
#80000
b1000 %
