03_combinational_circuits/mux/mind_blowing-ishh/main.v
// ============================================================
// 2048-to-1 Multiplexer
//   - 2048 single-bit data inputs (data_in[2047:0])
//   - 11-bit select line (2^11 = 2048)
//   - 1-bit output
// ============================================================
module mux2048to1 (
    input  wire [2047:0] data_in,   // 2048 data inputs, 1 bit each
    input  wire [10:0]   sel,       // select line, log2(2048) = 11 bits
    output wire          dout       // selected output bit
);

    // Simple bit-select implementation.
    // data_in[sel] picks out the single bit addressed by sel.
    assign dout = data_in[sel];

endmodule


`timescale 1ns / 1ps
// ============================================================
// Testbench for mux2048to1
//   - Drives a randomized 2048-bit data vector
//   - Sweeps the select line through every value 0..2047
//   - Checks dout against the expected bit each time
//   - Also runs a few random (data, sel) trials for extra coverage
// ============================================================
module mux2048to1_tb;

    reg  [2047:0] data_in;
    reg  [10:0]   sel;
    wire          dout;

    integer i;
    integer errors;
    reg     expected;

    // Instantiate the DUT (device under test)
    mux2048to1 DUT (
        .data_in (data_in),
        .sel     (sel),
        .dout    (dout)
    );

    initial begin
        // Waveform dump for viewing in GTKWave, if desired
        $dumpfile("mux2048to1_tb.vcd");
        $dumpvars(0, mux2048to1_tb);

        errors = 0;

        // ---- Randomize the full 2048-bit data vector ----
        for (i = 0; i < 64; i = i + 1) begin
            // Fill 32 bits at a time (2048 / 32 = 64 chunks)
            data_in[i*32 +: 32] = $random;
        end

        $display("=================================================");
        $display(" Starting exhaustive select sweep (0 to 2047)");
        $display("=================================================");

        // ---- Exhaustive sweep over every select value ----
        for (i = 0; i < 2048; i = i + 1) begin
            sel = i[10:0];
            #5; // allow combinational logic to settle
            expected = data_in[i];
            if (dout !== expected) begin
                errors = errors + 1;
                $display("MISMATCH at sel=%0d: dout=%b expected=%b",
                          i, dout, expected);
            end
        end

        $display("Exhaustive sweep complete. Errors so far: %0d", errors);

        // ---- A few extra random (data, sel) trials ----
        $display("=================================================");
        $display(" Running randomized trials");
        $display("=================================================");
        for (i = 0; i < 20; i = i + 1) begin
            data_in[i*32 +: 32] = $random; // re-randomize a chunk
            data_in[(63-i)*32 +: 32] = $random;
            sel = $random % 2048;
            #5;
            expected = data_in[sel];
            if (dout !== expected) begin
                errors = errors + 1;
                $display("RANDOM TRIAL MISMATCH at sel=%0d: dout=%b expected=%b",
                          sel, dout, expected);
            end else begin
                $display("Trial %0d OK: sel=%0d dout=%b", i, sel, dout);
            end
        end

        $display("=================================================");
        if (errors == 0)
            $display(" ALL TESTS PASSED (2048-to-1 mux verified)");
        else
            $display(" TESTS FAILED: %0d mismatches found", errors);
        $display("=================================================");

        $finish;
    end

endmodule

03_combinational_circuits/mux/mind_blowing-ishh/mux2048to1_tb.vcd
$date
	Tue Sep 15 18:28:20 2026
$end
$version
	Icarus Verilog
$end
$timescale
	1ps
$end
$scope module mux2048to1_tb $end
$var wire 1 ! dout $end
$var reg 2048 " data_in [2047:0] $end
$var reg 1 # expected $end
$var reg 11 $ sel [10:0] $end
$var integer 32 % errors [31:0] $end
$var integer 32 & i [31:0] $end
$scope module DUT $end
$var wire 2048 ' data_in [2047:0] $end
$var wire 11 ( sel [10:0] $end
$var wire 1 ! dout $end
$upscope $end
$upscope $end
$enddefinitions $end
$comment Show the parameter values. $end
$dumpall
$end
#0
$dumpvars
b0 (
b10111000100101111011111001110001100001011101011110011010000010110001010100001111110111010010101011011110011101010000001010111100010101110001010100010011101011100110001101001011111110011100011001011011000000100110010110110110011101011100010100001101111010111100010010001010000100101000100100111100001000001111001101111000111011000100101100110100110110000010000011000100101100110100000101000101001011100110000110001010011110010110100010111101111100101001111000110001010011000011110011100101011100110000101011001010000001010000100101100101000010100001000110000100010010010010001111100111110001010111001011001111000011101111111111101001000111011101011101010110001111101010111010000001000101110100101000000010111010101010011000101010110101010011010110011111110111010110101110101001101001111101011001010011100001101011110000111000000011011000100110000011101110000001001111001011001000000011111010010110110011101100110011001100100111010101010101111000010001011010101000010000011001000010000100100000110000000011101100100010100000000000010101110011100001110000101010110001111011110110001001100011101100101010011100100110011001011001011010101011010110000010110111011110100011100010100010111101001011100101100001001001010111001110001011001010010011101100010111110100000000000111101011101000111001110111011010010110110011100111100100110000011010011111001001000111111011001101101110001111100010010011001011010110000100101011101111010010011100100111011101110010101011111111011111100101110101010001001111010010101010101110001011110111100001001100010111100011001101110010010011000110011111001111110111101001111110010100011000101101111101111000110001110110110101000101011111101101000111101000110111001101001111010011101100100011111100010111011000000110110101111100110100001101000000001111001111100011000000011000100100110111010100100001001010110010110000101000010001100101010001101101111110011001100011010000011010111001011110110000110110110001111100000101011001100011100001001000010011010110000010011100000010001001010111101000000100010010000101010011010100100100 '
b0 &
b0 %
b0 $
x#
b10111000100101111011111001110001100001011101011110011010000010110001010100001111110111010010101011011110011101010000001010111100010101110001010100010011101011100110001101001011111110011100011001011011000000100110010110110110011101011100010100001101111010111100010010001010000100101000100100111100001000001111001101111000111011000100101100110100110110000010000011000100101100110100000101000101001011100110000110001010011110010110100010111101111100101001111000110001010011000011110011100101011100110000101011001010000001010000100101100101000010100001000110000100010010010010001111100111110001010111001011001111000011101111111111101001000111011101011101010110001111101010111010000001000101110100101000000010111010101010011000101010110101010011010110011111110111010110101110101001101001111101011001010011100001101011110000111000000011011000100110000011101110000001001111001011001000000011111010010110110011101100110011001100100111010101010101111000010001011010101000010000011001000010000100100000110000000011101100100010100000000000010101110011100001110000101010110001111011110110001001100011101100101010011100100110011001011001011010101011010110000010110111011110100011100010100010111101001011100101100001001001010111001110001011001010010011101100010111110100000000000111101011101000111001110111011010010110110011100111100100110000011010011111001001000111111011001101101110001111100010010011001011010110000100101011101111010010011100100111011101110010101011111111011111100101110101010001001111010010101010101110001011110111100001001100010111100011001101110010010011000110011111001111110111101001111110010100011000101101111101111000110001110110110101000101011111101101000111101000110111001101001111010011101100100011111100010111011000000110110101111100110100001101000000001111001111100011000000011000100100110111010100100001001010110010110000101000010001100101010001101101111110011001100011010000011010111001011110110000110110110001111100000101011001100011100001001000010011010110000010011100000010001001010111101000000100010010000101010011010100100100 "
0!
$end
#5000
b1 $
b1 (
b1 &
0#
#10000
1!
b10 $
b10 (
b10 &
#15000
0!
b11 $
b11 (
b11 &
1#
#20000
b100 $
b100 (
b100 &
0#
#25000
1!
b101 $
b101 (
b101 &
#30000
0!
b110 $
b110 (
b110 &
1#
#35000
b111 $
b111 (
b111 &
0#
#40000
1!
b1000 $
b1000 (
b1000 &
#45000
0!
b1001 $
b1001 (
b1001 &
1#
#50000
1!
b1010 $
b1010 (
b1010 &
0#
#55000
0!
b1011 $
b1011 (
b1011 &
1#
#60000
1!
b1100 $
b1100 (
b1100 &
0#
#65000
b1101 $
b1101 (
b1101 &
1#
#70000
0!
b1110 $
b1110 (
b1110 &
#75000
b1111 $
b1111 (
b1111 &
0#
#80000
1!
b10000 $
b10000 (
b10000 &
#85000
0!
b10001 $
b10001 (
b10001 &
1#
#90000
1!
b10010 $
b10010 (
b10010 &
0#
#95000
0!
b10011 $
b10011 (
b10011 &
1#
#100000
1!
b10100 $
b10100 (
b10100 &
0#
#105000
0!
b10101 $
b10101 (
b10101 &
1#
#110000
b10110 $
b10110 (
b10110 &
0#
#115000
b10111 $
b10111 (
b10111 &
#120000
b11000 $
b11000 (
b11000 &
#125000
1!
b11001 $
b11001 (
b11001 &
#130000
0!
b11010 $
b11010 (
b11010 &
1#
#135000
b11011 $
b11011 (
b11011 &
0#
#140000
1!
b11100 $
b11100 (
b11100 &
#145000
0!
b11101 $
b11101 (
b11101 &
1#
#150000
b11110 $
b11110 (
b11110 &
0#
#155000
b11111 $
b11111 (
b11111 &
#160000
1!
b100000 $
b100000 (
b100000 &
#165000
0!
b100001 $
b100001 (
b100001 &
1#
#170000
b100010 $
b100010 (
b100010 &
0#
#175000
b100011 $
b100011 (
b100011 &
#180000
b100100 $
b100100 (
b100100 &
#185000
b100101 $
b100101 (
b100101 &
#190000
b100110 $
b100110 (
b100110 &
#195000
1!
b100111 $
b100111 (
b100111 &
#200000
0!
b101000 $
b101000 (
b101000 &
1#
#205000
1!
b101001 $
b101001 (
b101001 &
0#
#210000
b101010 $
b101010 (
b101010 &
1#
#215000
b101011 $
b101011 (
b101011 &
#220000
b101100 $
b101100 (
b101100 &
#225000
0!
b101101 $
b101101 (
b101101 &
#230000
1!
b101110 $
b101110 (
b101110 &
0#
#235000
0!
b101111 $
b101111 (
b101111 &
1#
#240000
1!
b110000 $
b110000 (
b110000 &
0#
#245000
0!
b110001 $
b110001 (
b110001 &
1#
#250000
b110010 $
b110010 (
b110010 &
0#
#255000
1!
b110011 $
b110011 (
b110011 &
#260000
0!
b110100 $
b110100 (
b110100 &
1#
#265000
b110101 $
b110101 (
b110101 &
0#
#270000
b110110 $
b110110 (
b110110 &
#275000
1!
b110111 $
b110111 (
b110111 &
#280000
0!
b111000 $
b111000 (
b111000 &
1#
#285000
b111001 $
b111001 (
b111001 &
0#
#290000
b111010 $
b111010 (
b111010 &
#295000
b111011 $
b111011 (
b111011 &
#300000
b111100 $
b111100 (
b111100 &
#305000
b111101 $
b111101 (
b111101 &
#310000
1!
b111110 $
b111110 (
b111110 &
#315000
b111111 $
b111111 (
b111111 &
1#
#320000
b1000000 $
b1000000 (
b1000000 &
#325000
0!
b1000001 $
b1000001 (
b1000001 &
#330000
b1000010 $
b1000010 (
b1000010 &
0#
#335000
1!
b1000011 $
b1000011 (
b1000011 &
#340000
0!
b1000100 $
b1000100 (
b1000100 &
1#
#345000
b1000101 $
b1000101 (
b1000101 &
0#
#350000
b1000110 $
b1000110 (
b1000110 &
#355000
b1000111 $
b1000111 (
b1000111 &
#360000
b1001000 $
b1001000 (
b1001000 &
#365000
1!
b1001001 $
b1001001 (
b1001001 &
#370000
b1001010 $
b1001010 (
b1001010 &
1#
#375000
0!
b1001011 $
b1001011 (
b1001011 &
#380000
1!
b1001100 $
b1001100 (
b1001100 &
0#
#385000
0!
b1001101 $
b1001101 (
b1001101 &
1#
#390000
1!
b1001110 $
b1001110 (
b1001110 &
0#
#395000
b1001111 $
b1001111 (
b1001111 &
1#
#400000
0!
b1010000 $
b1010000 (
b1010000 &
#405000
b1010001 $
b1010001 (
b1010001 &
0#
#410000
1!
b1010010 $
b1010010 (
b1010010 &
#415000
0!
b1010011 $
b1010011 (
b1010011 &
1#
#420000
b1010100 $
b1010100 (
b1010100 &
0#
#425000
b1010101 $
b1010101 (
b1010101 &
#430000
b1010110 $
b1010110 (
b1010110 &
#435000
1!
b1010111 $
b1010111 (
b1010111 &
#440000
0!
b1011000 $
b1011000 (
b1011000 &
1#
#445000
b1011001 $
b1011001 (
b1011001 &
0#
#450000
1!
b1011010 $
b1011010 (
b1011010 &
#455000
0!
b1011011 $
b1011011 (
b1011011 &
1#
#460000
b1011100 $
b1011100 (
b1011100 &
0#
#465000
b1011101 $
b1011101 (
b1011101 &
#470000
b1011110 $
b1011110 (
b1011110 &
#475000
1!
b1011111 $
b1011111 (
b1011111 &
#480000
b1100000 $
b1100000 (
b1100000 &
1#
#485000
b1100001 $
b1100001 (
b1100001 &
#490000
0!
b1100010 $
b1100010 (
b1100010 &
#495000
b1100011 $
b1100011 (
b1100011 &
0#
#500000
b1100100 $
b1100100 (
b1100100 &
#505000
1!
b1100101 $
b1100101 (
b1100101 &
#510000
b1100110 $
b1100110 (
b1100110 &
1#
#515000
0!
b1100111 $
b1100111 (
b1100111 &
#520000
b1101000 $
b1101000 (
b1101000 &
0#
#525000
1!
b1101001 $
b1101001 (
b1101001 &
#530000
b1101010 $
b1101010 (
b1101010 &
1#
#535000
0!
b1101011 $
b1101011 (
b1101011 &
#540000
1!
b1101100 $
b1101100 (
b1101100 &
0#
#545000
0!
b1101101 $
b1101101 (
b1101101 &
1#
#550000
1!
b1101110 $
b1101110 (
b1101110 &
0#
#555000
0!
b1101111 $
b1101111 (
b1101111 &
1#
#560000
b1110000 $
b1110000 (
b1110000 &
0#
#565000
b1110001 $
b1110001 (
b1110001 &
#570000
b1110010 $
b1110010 (
b1110010 &
#575000
b1110011 $
b1110011 (
b1110011 &
#580000
1!
b1110100 $
b1110100 (
b1110100 &
#585000
b1110101 $
b1110101 (
b1110101 &
1#
#590000
b1110110 $
b1110110 (
b1110110 &
#595000
b1110111 $
b1110111 (
b1110111 &
#600000
b1111000 $
b1111000 (
b1111000 &
#605000
0!
b1111001 $
b1111001 (
b1111001 &
#610000
b1111010 $
b1111010 (
b1111010 &
0#
#615000
b1111011 $
b1111011 (
b1111011 &
#620000
1!
b1111100 $
b1111100 (
b1111100 &
#625000
b1111101 $
b1111101 (
b1111101 &
1#
#630000
0!
b1111110 $
b1111110 (
b1111110 &
#635000
1!
b1111111 $
b1111111 (
b1111111 &
0#
#640000
b10000000 $
b10000000 (
b10000000 &
1#
#645000
0!
b10000001 $
b10000001 (
b10000001 &
#650000
1!
b10000010 $
b10000010 (
b10000010 &
0#
#655000
b10000011 $
b10000011 (
b10000011 &
1#
#660000
0!
b10000100 $
b10000100 (
b10000100 &
#665000
b10000101 $
b10000101 (
b10000101 &
0#
#670000
b10000110 $
b10000110 (
b10000110 &
#675000
b10000111 $
b10000111 (
b10000111 &
#680000
1!
b10001000 $
b10001000 (
b10001000 &
#685000
b10001001 $
b10001001 (
b10001001 &
1#
#690000
0!
b10001010 $
b10001010 (
b10001010 &
#695000
1!
b10001011 $
b10001011 (
b10001011 &
0#
#700000
b10001100 $
b10001100 (
b10001100 &
1#
#705000
b10001101 $
b10001101 (
b10001101 &
#710000
b10001110 $
b10001110 (
b10001110 &
#715000
0!
b10001111 $
b10001111 (
b10001111 &
#720000
1!
b10010000 $
b10010000 (
b10010000 &
0#
#725000
0!
b10010001 $
b10010001 (
b10010001 &
1#
#730000
b10010010 $
b10010010 (
b10010010 &
0#
#735000
1!
b10010011 $
b10010011 (
b10010011 &
#740000
b10010100 $
b10010100 (
b10010100 &
1#
#745000
b10010101 $
b10010101 (
b10010101 &
#750000
0!
b10010110 $
b10010110 (
b10010110 &
#755000
1!
b10010111 $
b10010111 (
b10010111 &
0#
#760000
0!
b10011000 $
b10011000 (
b10011000 &
1#
#765000
1!
b10011001 $
b10011001 (
b10011001 &
0#
#770000
b10011010 $
b10011010 (
b10011010 &
1#
#775000
0!
b10011011 $
b10011011 (
b10011011 &
#780000
b10011100 $
b10011100 (
b10011100 &
0#
#785000
b10011101 $
b10011101 (
b10011101 &
#790000
b10011110 $
b10011110 (
b10011110 &
#795000
b10011111 $
b10011111 (
b10011111 &
#800000
1!
b10100000 $
b10100000 (
b10100000 &
#805000
0!
b10100001 $
b10100001 (
b10100001 &
1#
#810000
1!
b10100010 $
b10100010 (
b10100010 &
0#
#815000
b10100011 $
b10100011 (
b10100011 &
1#
#820000
0!
b10100100 $
b10100100 (
b10100100 &
#825000
b10100101 $
b10100101 (
b10100101 &
0#
#830000
b10100110 $
b10100110 (
b10100110 &
#835000
1!
b10100111 $
b10100111 (
b10100111 &
#840000
b10101000 $
b10101000 (
b10101000 &
1#
#845000
0!
b10101001 $
b10101001 (
b10101001 &
#850000
b10101010 $
b10101010 (
b10101010 &
0#
#855000
1!
b10101011 $
b10101011 (
b10101011 &
#860000
b10101100 $
b10101100 (
b10101100 &
1#
#865000
0!
b10101101 $
b10101101 (
b10101101 &
#870000
b10101110 $
b10101110 (
b10101110 &
0#
#875000
1!
b10101111 $
b10101111 (
b10101111 &
#880000
b10110000 $
b10110000 (
b10110000 &
1#
#885000
b10110001 $
b10110001 (
b10110001 &
#890000
b10110010 $
b10110010 (
b10110010 &
#895000
b10110011 $
b10110011 (
b10110011 &
#900000
b10110100 $
b10110100 (
b10110100 &
#905000
0!
b10110101 $
b10110101 (
b10110101 &
#910000
1!
b10110110 $
b10110110 (
b10110110 &
0#
#915000
b10110111 $
b10110111 (
b10110111 &
1#
#920000
0!
b10111000 $
b10111000 (
b10111000 &
#925000
1!
b10111001 $
b10111001 (
b10111001 &
0#
#930000
b10111010 $
b10111010 (
b10111010 &
1#
#935000
0!
b10111011 $
b10111011 (
b10111011 &
#940000
b10111100 $
b10111100 (
b10111100 &
0#
#945000
b10111101 $
b10111101 (
b10111101 &
#950000
1!
b10111110 $
b10111110 (
b10111110 &
#955000
0!
b10111111 $
b10111111 (
b10111111 &
1#
#960000
1!
b11000000 $
b11000000 (
b11000000 &
0#
#965000
0!
b11000001 $
b11000001 (
b11000001 &
1#
#970000
1!
b11000010 $
b11000010 (
b11000010 &
0#
#975000
0!
b11000011 $
b11000011 (
b11000011 &
1#
#980000
b11000100 $
b11000100 (
b11000100 &
0#
#985000
1!
b11000101 $
b11000101 (
b11000101 &
#990000
b11000110 $
b11000110 (
b11000110 &
1#
#995000
0!
b11000111 $
b11000111 (
b11000111 &
#1000000
b11001000 $
b11001000 (
b11001000 &
0#
#1005000
b11001001 $
b11001001 (
b11001001 &
#1010000
1!
b11001010 $
b11001010 (
b11001010 &
#1015000
0!
b11001011 $
b11001011 (
b11001011 &
1#
#1020000
b11001100 $
b11001100 (
b11001100 &
0#
#1025000
b11001101 $
b11001101 (
b11001101 &
#1030000
b11001110 $
b11001110 (
b11001110 &
#1035000
1!
b11001111 $
b11001111 (
b11001111 &
#1040000
0!
b11010000 $
b11010000 (
b11010000 &
1#
#1045000
1!
b11010001 $
b11010001 (
b11010001 &
0#
#1050000
0!
b11010010 $
b11010010 (
b11010010 &
1#
#1055000
b11010011 $
b11010011 (
b11010011 &
0#
#1060000
b11010100 $
b11010100 (
b11010100 &
#1065000
b11010101 $
b11010101 (
b11010101 &
#1070000
1!
b11010110 $
b11010110 (
b11010110 &
#1075000
b11010111 $
b11010111 (
b11010111 &
1#
#1080000
0!
b11011000 $
b11011000 (
b11011000 &
#1085000
1!
b11011001 $
b11011001 (
b11011001 &
0#
#1090000
0!
b11011010 $
b11011010 (
b11011010 &
1#
#1095000
b11011011 $
b11011011 (
b11011011 &
0#
#1100000
1!
b11011100 $
b11011100 (
b11011100 &
#1105000
b11011101 $
b11011101 (
b11011101 &
1#
#1110000
0!
b11011110 $
b11011110 (
b11011110 &
#1115000
1!
b11011111 $
b11011111 (
b11011111 &
0#
#1120000
0!
b11100000 $
b11100000 (
b11100000 &
1#
#1125000
1!
b11100001 $
b11100001 (
b11100001 &
0#
#1130000
0!
b11100010 $
b11100010 (
b11100010 &
1#
#1135000
b11100011 $
b11100011 (
b11100011 &
0#
#1140000
1!
b11100100 $
b11100100 (
b11100100 &
#1145000
0!
b11100101 $
b11100101 (
b11100101 &
1#
#1150000
b11100110 $
b11100110 (
b11100110 &
0#
#1155000
b11100111 $
b11100111 (
b11100111 &
#1160000
b11101000 $
b11101000 (
b11101000 &
#1165000
1!
b11101001 $
b11101001 (
b11101001 &
#1170000
0!
b11101010 $
b11101010 (
b11101010 &
1#
#1175000
b11101011 $
b11101011 (
b11101011 &
0#
#1180000
1!
b11101100 $
b11101100 (
b11101100 &
#1185000
0!
b11101101 $
b11101101 (
b11101101 &
1#
#1190000
1!
b11101110 $
b11101110 (
b11101110 &
0#
#1195000
0!
b11101111 $
b11101111 (
b11101111 &
1#
#1200000
1!
b11110000 $
b11110000 (
b11110000 &
0#
#1205000
b11110001 $
b11110001 (
b11110001 &
1#
#1210000
b11110010 $
b11110010 (
b11110010 &
#1215000
0!
b11110011 $
b11110011 (
b11110011 &
#1220000
1!
b11110100 $
b11110100 (
b11110100 &
0#
#1225000
b11110101 $
b11110101 (
b11110101 &
1#
#1230000
0!
b11110110 $
b11110110 (
b11110110 &
#1235000
b11110111 $
b11110111 (
b11110111 &
0#
#1240000
1!
b11111000 $
b11111000 (
b11111000 &
#1245000
0!
b11111001 $
b11111001 (
b11111001 &
1#
#1250000
b11111010 $
b11111010 (
b11111010 &
0#
#1255000
1!
b11111011 $
b11111011 (
b11111011 &
#1260000
0!
b11111100 $
b11111100 (
b11111100 &
1#
#1265000
b11111101 $
b11111101 (
b11111101 &
0#
#1270000
b11111110 $
b11111110 (
b11111110 &
#1275000
1!
b11111111 $
b11111111 (
b11111111 &
#1280000
b100000000 $
b100000000 (
b100000000 &
1#
#1285000
0!
b100000001 $
b100000001 (
b100000001 &
#1290000
b100000010 $
b100000010 (
b100000010 &
0#
#1295000
b100000011 $
b100000011 (
b100000011 &
#1300000
b100000100 $
b100000100 (
b100000100 &
#1305000
b100000101 $
b100000101 (
b100000101 &
#1310000
b100000110 $
b100000110 (
b100000110 &
#1315000
b100000111 $
b100000111 (
b100000111 &
#1320000
1!
b100001000 $
b100001000 (
b100001000 &
#1325000
b100001001 $
b100001001 (
b100001001 &
1#
#1330000
0!
b100001010 $
b100001010 (
b100001010 &
#1335000
b100001011 $
b100001011 (
b100001011 &
0#
#1340000
b100001100 $
b100001100 (
b100001100 &
#1345000
1!
b100001101 $
b100001101 (
b100001101 &
#1350000
b100001110 $
b100001110 (
b100001110 &
1#
#1355000
b100001111 $
b100001111 (
b100001111 &
#1360000
b100010000 $
b100010000 (
b100010000 &
#1365000
b100010001 $
b100010001 (
b100010001 &
#1370000
0!
b100010010 $
b100010010 (
b100010010 &
#1375000
b100010011 $
b100010011 (
b100010011 &
0#
#1380000
1!
b100010100 $
b100010100 (
b100010100 &
#1385000
b100010101 $
b100010101 (
b100010101 &
1#
#1390000
b100010110 $
b100010110 (
b100010110 &
#1395000
b100010111 $
b100010111 (
b100010111 &
#1400000
0!
b100011000 $
b100011000 (
b100011000 &
#1405000
b100011001 $
b100011001 (
b100011001 &
0#
#1410000
b100011010 $
b100011010 (
b100011010 &
#1415000
b100011011 $
b100011011 (
b100011011 &
#1420000
b100011100 $
b100011100 (
b100011100 &
#1425000
b100011101 $
b100011101 (
b100011101 &
#1430000
b100011110 $
b100011110 (
b100011110 &
#1435000
b100011111 $
b100011111 (
b100011111 &
#1440000
1!
b100100000 $
b100100000 (
b100100000 &
#1445000
0!
b100100001 $
b100100001 (
b100100001 &
1#
#1450000
1!
b100100010 $
b100100010 (
b100100010 &
0#
#1455000
b100100011 $
b100100011 (
b100100011 &
1#
#1460000
0!
b100100100 $
b100100100 (
b100100100 &
#1465000
b100100101 $
b100100101 (
b100100101 &
0#
#1470000
b100100110 $
b100100110 (
b100100110 &
#1475000
b100100111 $
b100100111 (
b100100111 &
#1480000
1!
b100101000 $
b100101000 (
b100101000 &
#1485000
0!
b100101001 $
b100101001 (
b100101001 &
1#
#1490000
1!
b100101010 $
b100101010 (
b100101010 &
0#
#1495000
b100101011 $
b100101011 (
b100101011 &
1#
#1500000
0!
b100101100 $
b100101100 (
b100101100 &
#1505000
b100101101 $
b100101101 (
b100101101 &
0#
#1510000
1!
b100101110 $
b100101110 (
b100101110 &
#1515000
b100101111 $
b100101111 (
b100101111 &
1#
#1520000
b100110000 $
b100110000 (
b100110000 &
#1525000
b100110001 $
b100110001 (
b100110001 &
#1530000
b100110010 $
b100110010 (
b100110010 &
#1535000
0!
b100110011 $
b100110011 (
b100110011 &
#1540000
1!
b100110100 $
b100110100 (
b100110100 &
0#
#1545000
0!
b100110101 $
b100110101 (
b100110101 &
1#
#1550000
1!
b100110110 $
b100110110 (
b100110110 &
0#
#1555000
b100110111 $
b100110111 (
b100110111 &
1#
#1560000
0!
b100111000 $
b100111000 (
b100111000 &
#1565000
1!
b100111001 $
b100111001 (
b100111001 &
0#
#1570000
b100111010 $
b100111010 (
b100111010 &
1#
#1575000
0!
b100111011 $
b100111011 (
b100111011 &
#1580000
b100111100 $
b100111100 (
b100111100 &
0#
#1585000
b100111101 $
b100111101 (
b100111101 &
#1590000
b100111110 $
b100111110 (
b100111110 &
#1595000
b100111111 $
b100111111 (
b100111111 &
#1600000
b101000000 $
b101000000 (
b101000000 &
#1605000
1!
b101000001 $
b101000001 (
b101000001 &
#1610000
b101000010 $
b101000010 (
b101000010 &
1#
#1615000
0!
b101000011 $
b101000011 (
b101000011 &
#1620000
1!
b101000100 $
b101000100 (
b101000100 &
0#
#1625000
b101000101 $
b101000101 (
b101000101 &
1#
#1630000
b101000110 $
b101000110 (
b101000110 &
#1635000
0!
b101000111 $
b101000111 (
b101000111 &
#1640000
1!
b101001000 $
b101001000 (
b101001000 &
0#
#1645000
0!
b101001001 $
b101001001 (
b101001001 &
1#
#1650000
b101001010 $
b101001010 (
b101001010 &
0#
#1655000
b101001011 $
b101001011 (
b101001011 &
#1660000
1!
b101001100 $
b101001100 (
b101001100 &
#1665000
b101001101 $
b101001101 (
b101001101 &
1#
#1670000
b101001110 $
b101001110 (
b101001110 &
#1675000
b101001111 $
b101001111 (
b101001111 &
#1680000
b101010000 $
b101010000 (
b101010000 &
#1685000
b101010001 $
b101010001 (
b101010001 &
#1690000
0!
b101010010 $
b101010010 (
b101010010 &
#1695000
b101010011 $
b101010011 (
b101010011 &
0#
#1700000
b101010100 $
b101010100 (
b101010100 &
#1705000
1!
b101010101 $
b101010101 (
b101010101 &
#1710000
0!
b101010110 $
b101010110 (
b101010110 &
1#
#1715000
b101010111 $
b101010111 (
b101010111 &
0#
#1720000
1!
b101011000 $
b101011000 (
b101011000 &
#1725000
b101011001 $
b101011001 (
b101011001 &
1#
#1730000
0!
b101011010 $
b101011010 (
b101011010 &
#1735000
1!
b101011011 $
b101011011 (
b101011011 &
0#
#1740000
b101011100 $
b101011100 (
b101011100 &
1#
#1745000
b101011101 $
b101011101 (
b101011101 &
#1750000
0!
b101011110 $
b101011110 (
b101011110 &
#1755000
b101011111 $
b101011111 (
b101011111 &
0#
#1760000
1!
b101100000 $
b101100000 (
b101100000 &
#1765000
0!
b101100001 $
b101100001 (
b101100001 &
1#
#1770000
1!
b101100010 $
b101100010 (
b101100010 &
0#
#1775000
b101100011 $
b101100011 (
b101100011 &
1#
#1780000
b101100100 $
b101100100 (
b101100100 &
#1785000
b101100101 $
b101100101 (
b101100101 &
#1790000
0!
b101100110 $
b101100110 (
b101100110 &
#1795000
b101100111 $
b101100111 (
b101100111 &
0#
#1800000
1!
b101101000 $
b101101000 (
b101101000 &
#1805000
0!
b101101001 $
b101101001 (
b101101001 &
1#
#1810000
1!
b101101010 $
b101101010 (
b101101010 &
0#
#1815000
b101101011 $
b101101011 (
b101101011 &
1#
#1820000
0!
b101101100 $
b101101100 (
b101101100 &
#1825000
b101101101 $
b101101101 (
b101101101 &
0#
#1830000
1!
b101101110 $
b101101110 (
b101101110 &
#1835000
b101101111 $
b101101111 (
b101101111 &
1#
#1840000
b101110000 $
b101110000 (
b101110000 &
#1845000
0!
b101110001 $
b101110001 (
b101110001 &
#1850000
1!
b101110010 $
b101110010 (
b101110010 &
0#
#1855000
b101110011 $
b101110011 (
b101110011 &
1#
#1860000
0!
b101110100 $
b101110100 (
b101110100 &
#1865000
b101110101 $
b101110101 (
b101110101 &
0#
#1870000
b101110110 $
b101110110 (
b101110110 &
#1875000
1!
b101110111 $
b101110111 (
b101110111 &
#1880000
0!
b101111000 $
b101111000 (
b101111000 &
1#
#1885000
1!
b101111001 $
b101111001 (
b101111001 &
0#
#1890000
b101111010 $
b101111010 (
b101111010 &
1#
#1895000
b101111011 $
b101111011 (
b101111011 &
#1900000
b101111100 $
b101111100 (
b101111100 &
#1905000
0!
b101111101 $
b101111101 (
b101111101 &
#1910000
b101111110 $
b101111110 (
b101111110 &
0#
#1915000
b101111111 $
b101111111 (
b101111111 &
#1920000
1!
b110000000 $
b110000000 (
b110000000 &
#1925000
0!
b110000001 $
b110000001 (
b110000001 &
1#
#1930000
1!
b110000010 $
b110000010 (
b110000010 &
0#
#1935000
b110000011 $
b110000011 (
b110000011 &
1#
#1940000
0!
b110000100 $
b110000100 (
b110000100 &
#1945000
1!
b110000101 $
b110000101 (
b110000101 &
0#
#1950000
b110000110 $
b110000110 (
b110000110 &
1#
#1955000
b110000111 $
b110000111 (
b110000111 &
#1960000
b110001000 $
b110001000 (
b110001000 &
#1965000
b110001001 $
b110001001 (
b110001001 &
#1970000
b110001010 $
b110001010 (
b110001010 &
#1975000
0!
b110001011 $
b110001011 (
b110001011 &
#1980000
1!
b110001100 $
b110001100 (
b110001100 &
0#
#1985000
0!
b110001101 $
b110001101 (
b110001101 &
1#
#1990000
1!
b110001110 $
b110001110 (
b110001110 &
0#
#1995000
0!
b110001111 $
b110001111 (
b110001111 &
1#
#2000000
b110010000 $
b110010000 (
b110010000 &
0#
#2005000
b110010001 $
b110010001 (
b110010001 &
#2010000
1!
b110010010 $
b110010010 (
b110010010 &
#2015000
0!
b110010011 $
b110010011 (
b110010011 &
1#
#2020000
1!
b110010100 $
b110010100 (
b110010100 &
0#
#2025000
0!
b110010101 $
b110010101 (
b110010101 &
1#
#2030000
1!
b110010110 $
b110010110 (
b110010110 &
0#
#2035000
b110010111 $
b110010111 (
b110010111 &
1#
#2040000
0!
b110011000 $
b110011000 (
b110011000 &
#2045000
1!
b110011001 $
b110011001 (
b110011001 &
0#
#2050000
b110011010 $
b110011010 (
b110011010 &
1#
#2055000
0!
b110011011 $
b110011011 (
b110011011 &
#2060000
1!
b110011100 $
b110011100 (
b110011100 &
0#
#2065000
b110011101 $
b110011101 (
b110011101 &
1#
#2070000
b110011110 $
b110011110 (
b110011110 &
#2075000
0!
b110011111 $
b110011111 (
b110011111 &
#2080000
b110100000 $
b110100000 (
b110100000 &
0#
#2085000
b110100001 $
b110100001 (
b110100001 &
#2090000
1!
b110100010 $
b110100010 (
b110100010 &
#2095000
b110100011 $
b110100011 (
b110100011 &
1#
#2100000
0!
b110100100 $
b110100100 (
b110100100 &
#2105000
b110100101 $
b110100101 (
b110100101 &
0#
#2110000
b110100110 $
b110100110 (
b110100110 &
#2115000
1!
b110100111 $
b110100111 (
b110100111 &
#2120000
b110101000 $
b110101000 (
b110101000 &
1#
#2125000
b110101001 $
b110101001 (
b110101001 &
#2130000
b110101010 $
b110101010 (
b110101010 &
